Metadata-Version: 2.1
Name: odoo9-addon-base-geoengine
Version: 9.0.1.2.5.99.dev7
Summary: Geospatial support for Odoo
Home-page: http://openerp.camptocamp.com
Author: Camptocamp,ACSONE SA/NV,Odoo Community Association (OCA)
Author-email: support@odoo-community.org
License: AGPL-3
Platform: UNKNOWN
Classifier: Programming Language :: Python
Classifier: Framework :: Odoo
Classifier: Framework :: Odoo :: 9.0
Classifier: License :: OSI Approved :: GNU Affero General Public License v3
Requires-Python: ~=2.7
Requires-Dist: geojson
Requires-Dist: odoo (<9.1a,>=9.0a)
Requires-Dist: shapely
